pythle/__init__.py
pythle/cli.py
pythle/guess.py
pythle/load_wordlist.py
pythle/player_stats.py
pythle/pythle.py
pythle/data/solutions.txt
pythle/data/words.txt
pythle-0.1.2.dist-info/LICENSE
pythle-0.1.2.dist-info/METADATA
pythle-0.1.2.dist-info/WHEEL
pythle-0.1.2.dist-info/entry_points.txt
pythle-0.1.2.dist-info/top_level.txt
pythle-0.1.2.dist-info/RECORD
