Metadata-Version: 2.1
Name: pythle
Version: 0.1.2
Summary: A terminal-based version of the popular word-guessing game Wordle, built with Python. Created as my first GitHub project!
Home-page: https://github.com/TomJGooding/pythle
Author: Tom Gooding
License: UNKNOWN
Project-URL: Bug Tracker, https://github.com/TomJGooding/pythle/labels/bug
Platform: UNKNOWN
Classifier: Programming Language :: Python :: 3
Classifier: License :: OSI Approved :: GNU General Public License v3 (GPLv3)
Classifier: Operating System :: OS Independent
Requires-Python: >=3.6
License-File: LICENSE
